remove_duplicate_fastq_matepair/__init__.py
remove_duplicate_fastq_matepair/__main__.py
remove_duplicate_fastq_matepair/main.py
remove_duplicate_fastq_matepair/remove_duplicate_fastq_matepair.py
remove_duplicate_fastq_matepair-0.15.dist-info/DESCRIPTION.rst
remove_duplicate_fastq_matepair-0.15.dist-info/METADATA
remove_duplicate_fastq_matepair-0.15.dist-info/RECORD
remove_duplicate_fastq_matepair-0.15.dist-info/WHEEL
remove_duplicate_fastq_matepair-0.15.dist-info/metadata.json
remove_duplicate_fastq_matepair-0.15.dist-info/top_level.txt
