Metadata-Version: 2.0
Name: remove-duplicate-fastq-matepair
Version: 0.15
Summary: Remove duplicate mate pairs from a FASTQ
Home-page: https://github.com/jeremiahsavage/remove_duplicate_fastq_matepair
Author: Jeremiah H. Savage
Author-email: jeremiahsavage@gmail.com
License: Apache 2.0
Platform: UNKNOWN
Classifier: Development Status :: 3 - Alpha
Classifier: Intended Audience :: Developers
Classifier: License :: OSI Approved :: Apache Software License
Classifier: Programming Language :: Python
Classifier: Programming Language :: Python :: 2
Classifier: Programming Language :: Python :: 3
Requires-Dist: biopython
Requires-Dist: cdis-pipe-utils
Requires-Dist: cython
Requires-Dist: pandas
Requires-Dist: sqlalchemy
